monkey/dao/dao.py
monkey/dao/errors.py
monkey/dao/results.py
monkey/dao/util.py
monkey_dao-2.0.0.dev6.dist-info/licenses/LICENSE
monkey_dao-2.0.0.dev6.dist-info/METADATA
monkey_dao-2.0.0.dev6.dist-info/WHEEL
monkey_dao-2.0.0.dev6.dist-info/top_level.txt
monkey_dao-2.0.0.dev6.dist-info/RECORD
